<?xml version="1.0" encoding="UTF-8"?>
<objects serializationModel="Studio.02.02.00">
	<object class="AudioFile" id="{1535486c-0472-4cd1-92b8-5f2f8c1885d8}">
		<property name="assetPath">
			<value>Sound/alien_sounds/ES_Sci Fi Voice Clip 354 - SFX Producer.mp3</value>
		</property>
		<property name="frequencyInKHz">
			<value>48</value>
		</property>
		<property name="channelCount">
			<value>2</value>
		</property>
		<property name="length">
			<value>1.2</value>
		</property>
		<relationship name="masterAssetFolder">
			<destination>{c75f23a5-8c8b-4114-8a33-03ac63bb8f74}</destination>
		</relationship>
	</object>
</objects>
